mosaic_basis/__init__.py
mosaic_basis-0.2.0.dist-info/licenses/LICENSE
mosaic_basis-0.2.0.dist-info/METADATA
mosaic_basis-0.2.0.dist-info/WHEEL
mosaic_basis-0.2.0.dist-info/top_level.txt
mosaic_basis-0.2.0.dist-info/RECORD
