Metadata-Version: 2.4
Name: mosaic-basis
Version: 0.2.0
Summary: Forward-biased frame selection for OMP to reconstruct frame sequences and object trajectories as bases
Author-email: E Goughnour <e.goughnour@gmail.com>
Maintainer-email: E Goughnour <e.goughnour@gmail.com>
License: MIT
Project-URL: Homepage, https://github.com/egoughnour/mosaic-basis
Project-URL: Repository, https://github.com/egoughnour/mosaic-basis
Project-URL: Issues, https://github.com/egoughnour/mosaic-basis/issues
Keywords: mosaic,frame-selection,omp,trajectory
Classifier: Development Status :: 3 - Alpha
Classifier: Intended Audience :: Developers
Classifier: Intended Audience :: Science/Research
Classifier: License :: OSI Approved :: MIT License
Classifier: Programming Language :: Python :: 3
Classifier: Programming Language :: Python :: 3.9
Classifier: Programming Language :: Python :: 3.10
Classifier: Programming Language :: Python :: 3.11
Classifier: Programming Language :: Python :: 3.12
Classifier: Topic :: Scientific/Engineering
Requires-Python: >=3.9
License-File: LICENSE
Requires-Dist: opencv-python>=4.8.0
Requires-Dist: scikit-learn>=1.3.0
Requires-Dist: numpy>=1.24.0
Provides-Extra: dev
Requires-Dist: pytest>=7.0.0; extra == "dev"
Requires-Dist: pytest-cov>=4.0.0; extra == "dev"
Requires-Dist: black>=23.0.0; extra == "dev"
Requires-Dist: ruff>=0.1.0; extra == "dev"
Requires-Dist: mypy>=1.0.0; extra == "dev"
Requires-Dist: yt-dlp>=2024.7.25; extra == "dev"
Provides-Extra: yt
Requires-Dist: yt-dlp>=2024.7.25; extra == "yt"
Dynamic: license-file
